azure/mgmt/rdbms/__init__.py
azure/mgmt/rdbms/_version.py
azure/mgmt/rdbms/mariadb/__init__.py
azure/mgmt/rdbms/mariadb/_configuration.py
azure/mgmt/rdbms/mariadb/_maria_db_management_client.py
azure/mgmt/rdbms/mariadb/_version.py
azure/mgmt/rdbms/mariadb/aio/__init__.py
azure/mgmt/rdbms/mariadb/aio/_configuration.py
azure/mgmt/rdbms/mariadb/aio/_maria_db_management_client.py
azure/mgmt/rdbms/mariadb/aio/operations/__init__.py
azure/mgmt/rdbms/mariadb/aio/operations/_advisors_operations.py
azure/mgmt/rdbms/mariadb/aio/operations/_check_name_availability_operations.py
azure/mgmt/rdbms/mariadb/aio/operations/_configurations_operations.py
azure/mgmt/rdbms/mariadb/aio/operations/_databases_operations.py
azure/mgmt/rdbms/mariadb/aio/operations/_firewall_rules_operations.py
azure/mgmt/rdbms/mariadb/aio/operations/_location_based_performance_tier_operations.py
azure/mgmt/rdbms/mariadb/aio/operations/_location_based_recommended_action_sessions_operation_status_operations.py
azure/mgmt/rdbms/mariadb/aio/operations/_location_based_recommended_action_sessions_result_operations.py
azure/mgmt/rdbms/mariadb/aio/operations/_log_files_operations.py
azure/mgmt/rdbms/mariadb/aio/operations/_maria_db_management_client_operations.py
azure/mgmt/rdbms/mariadb/aio/operations/_operations.py
azure/mgmt/rdbms/mariadb/aio/operations/_private_endpoint_connections_operations.py
azure/mgmt/rdbms/mariadb/aio/operations/_private_link_resources_operations.py
azure/mgmt/rdbms/mariadb/aio/operations/_query_texts_operations.py
azure/mgmt/rdbms/mariadb/aio/operations/_recommended_actions_operations.py
azure/mgmt/rdbms/mariadb/aio/operations/_recoverable_servers_operations.py
azure/mgmt/rdbms/mariadb/aio/operations/_replicas_operations.py
azure/mgmt/rdbms/mariadb/aio/operations/_server_based_performance_tier_operations.py
azure/mgmt/rdbms/mariadb/aio/operations/_server_parameters_operations.py
azure/mgmt/rdbms/mariadb/aio/operations/_server_security_alert_policies_operations.py
azure_mgmt_rdbms-9.1.0.dist-info/METADATA
azure_mgmt_rdbms-9.1.0.dist-info/WHEEL
azure_mgmt_rdbms-9.1.0.dist-info/top_level.txt
azure_mgmt_rdbms-9.1.0.dist-info/RECORD
